Charm_tokenizer/Backbone.py
Charm_tokenizer/ImageProcessor.py
Charm_tokenizer/__init__.py
Charm_tokenizer/model.py
Charm_tokenizer-1.0.17.dist-info/LICENCE.txt
Charm_tokenizer-1.0.17.dist-info/METADATA
Charm_tokenizer-1.0.17.dist-info/WHEEL
Charm_tokenizer-1.0.17.dist-info/top_level.txt
Charm_tokenizer-1.0.17.dist-info/RECORD
