Metadata-Version: 2.1
Name: Charm-tokenizer
Version: 1.0.17
Summary: Official implementation of Charm tokenizer for ViTs
Home-page: https://github.com/FBehrad/Charm
Author: Fatemeh Behrad
Author-email: fatemehbehrad@yahoo.com
License: MIT
Classifier: License :: OSI Approved :: Apache Software License
Classifier: Programming Language :: Python :: 3.8
Classifier: Operating System :: OS Independent
Requires-Python: >=3.8
License-File: LICENCE.txt
Requires-Dist: huggingface-hub
Requires-Dist: timm==0.4.12
Requires-Dist: transformers==4.36.0
